mobility_graph/__init__.py
mobility_graph-0.0.5.dist-info/LICENSE
mobility_graph-0.0.5.dist-info/METADATA
mobility_graph-0.0.5.dist-info/WHEEL
mobility_graph-0.0.5.dist-info/top_level.txt
mobility_graph-0.0.5.dist-info/RECORD
