Metadata-Version: 2.1
Name: mobility-graph
Version: 0.0.5
Summary: This package has the necessary tools to read, analyze and turn mobility data into a graph object
Home-page: UNKNOWN
Author: Ayman Mahmoud
Author-email: aymanh.abdelhamid@gmail.com
License: UNKNOWN
Keywords: gtfs,transit,mobility
Platform: UNKNOWN
Classifier: Intended Audience :: Education
Classifier: Operating System :: OS Independent
Classifier: License :: OSI Approved :: MIT License
Classifier: Programming Language :: Python :: 3
Requires-Dist: networkx
Requires-Dist: matplotlib
Provides-Extra: dev
Requires-Dist: pytest (>=3.7) ; extra == 'dev'
